florana/__init__.py
florana/extract.py
florana/geography.txt
florana/key.json
florana/locations.txt
florana/test.py
florana_JOSIEST-1.1.43.dist-info/LICENSE
florana_JOSIEST-1.1.43.dist-info/METADATA
florana_JOSIEST-1.1.43.dist-info/WHEEL
florana_JOSIEST-1.1.43.dist-info/top_level.txt
florana_JOSIEST-1.1.43.dist-info/RECORD
