Metadata-Version: 2.1
Name: florana-JOSIEST
Version: 1.1.43
Summary: Extract data from Flora of North America
Home-page: https://github.com/josiest/Flora-Data-Extraction/
Author: Josie Thompson
Author-email: josiest@uw.edu
License: MIT
Platform: UNKNOWN
Classifier: Programming Language :: Python :: 3
Classifier: License :: OSI Approved :: MIT License
Classifier: Operating System :: OS Independent
Classifier: Intended Audience :: Science/Research
Requires-Python: >=3
